{
	"title-blog": "Blog",
	"menu-announcements": "Pengumuman",
	"menu-newsletters": "Surat Kabar",
	"menu-tweets": "Cuitan",
	"menu-articles": "Artikel",
	"menu-articles-forum": "Forum",
	"menu-articles-yearn": "Yearn.Finance",
	"menu-updates": "Kabar Terbaru",
	"menu-podcasts": "Podcasts",
	"menu-financials": "Keuangan",
	"menu-financials-quarterly-report": "Laporan Kuartal",
	"written-by": "Ditulis oleh",
	"translated-by": "Diterjemahkan oleh",
	"footer-contribute": "Berkontribusi",
	"footer-join": "Bergabung dengan Yearn",
	"footer-vault-at-yearn": "Lemari Besi di Yearn",
	"footer-disclaimer": "Penafian"
}
